whitebox_plugin_flight_annotations/pyproject.toml
whitebox_plugin_flight_annotations/__init__.py
whitebox_plugin_flight_annotations/apps.py
whitebox_plugin_flight_annotations/handlers.py
whitebox_plugin_flight_annotations/jsx/AnnotationCard.jsx
whitebox_plugin_flight_annotations/jsx/AnnotationCard.test.jsx
whitebox_plugin_flight_annotations/jsx/AnnotationInput.jsx
whitebox_plugin_flight_annotations/jsx/AnnotationInput.test.jsx
whitebox_plugin_flight_annotations/jsx/Annotations.jsx
whitebox_plugin_flight_annotations/jsx/AnnotationsOverlay.jsx
whitebox_plugin_flight_annotations/jsx/AnnotationsServiceComponent.jsx
whitebox_plugin_flight_annotations/jsx/Avatar.jsx
whitebox_plugin_flight_annotations/jsx/stores/annotations.js
whitebox_plugin_flight_annotations/migrations/0001_initial.py
whitebox_plugin_flight_annotations/migrations/__init__.py
whitebox_plugin_flight_annotations/models.py
whitebox_plugin_flight_annotations/serializers.py
whitebox_plugin_flight_annotations/services.py
whitebox_plugin_flight_annotations/whitebox_plugin_flight_annotations.py
whitebox_test_plugin_flight_annotations/__init__.py
whitebox_test_plugin_flight_annotations/test_handlers.py
whitebox_test_plugin_flight_annotations/test_models.py
whitebox_test_plugin_flight_annotations/test_services.py
whitebox_test_plugin_flight_annotations/test_whitebox_plugin_flight_annotations.py
whitebox_plugin_flight_annotations-0.1.3.dist-info/LICENSE
whitebox_plugin_flight_annotations-0.1.3.dist-info/METADATA
whitebox_plugin_flight_annotations-0.1.3.dist-info/WHEEL
whitebox_plugin_flight_annotations-0.1.3.dist-info/entry_points.txt
whitebox_plugin_flight_annotations-0.1.3.dist-info/RECORD
