Metadata-Version: 2.3
Name: whitebox-plugin-flight-annotations
Version: 0.1.3
Summary: A plugin for whitebox that enables flight annotations.
License: GNU Affero General Public License v3
Author: avilabss
Author-email: contact@avilabs.net
Requires-Python: >=3.10.0
Classifier: License :: Other/Proprietary License
Classifier: Programming Language :: Python :: 3
Classifier: Programming Language :: Python :: 3.10
Classifier: Programming Language :: Python :: 3.11
Classifier: Programming Language :: Python :: 3.12
Classifier: Programming Language :: Python :: 3.13
